dbdemos/__init__.py
dbdemos/conf.py
dbdemos/dbdemos.py
dbdemos/installer.py
dbdemos/installer_dashboard.py
dbdemos/installer_genie.py
dbdemos/installer_report.py
dbdemos/installer_repos.py
dbdemos/installer_workflows.py
dbdemos/job_bundler.py
dbdemos/notebook_parser.py
dbdemos/packager.py
dbdemos/sql_query.py
dbdemos/tracker.py
dbdemos/bundles/ai-agent/conf.json
dbdemos/bundles/ai-agent/install_package/01-ai-agent-introduction.html
dbdemos/bundles/ai-agent/install_package/config.html
dbdemos/bundles/ai-agent/install_package/01-create-tools/01_create_first_billing_agent.html
dbdemos/bundles/ai-agent/install_package/02-agent-eval/02.1_agent_evaluation.html
dbdemos/bundles/ai-agent/install_package/02-agent-eval/agent.py
dbdemos/bundles/ai-agent/install_package/03-knowledge-base-rag/03.1-pdf-rag-tool.html
dbdemos/bundles/ai-agent/install_package/04-deploy-app/04-Deploy-Frontend-Lakehouse-App.html
dbdemos/bundles/ai-agent/install_package/04-deploy-app/chatbot_app.zip
dbdemos/bundles/ai-agent/install_package/05-production-monitoring/05.production-monitoring.html
dbdemos/bundles/ai-agent/install_package/06-improving-business-kpis/06-business-dashboard.html
dbdemos/bundles/ai-agent/install_package/07-adding-mcp/07-agent_mcp.html
dbdemos/bundles/ai-agent/install_package/_resources/00-global-setup-v2.html
dbdemos/bundles/ai-agent/install_package/_resources/01-setup.html
dbdemos/bundles/ai-agent/install_package/_resources/02-data-generation.html
dbdemos/bundles/ai-agent/install_package/_resources/03-doc-pdf-documentation.html
dbdemos/bundles/ai-agent/install_package/_resources/04-eval-dataset-generation.html
dbdemos/bundles/aibi-customer-support/conf.json
dbdemos/bundles/aibi-customer-support/install_package/AI-BI-Customer-support.html
dbdemos/bundles/aibi-customer-support/install_package/_resources/dashboards/customer-support.lvdash.json
dbdemos/bundles/aibi-marketing-campaign/conf.json
dbdemos/bundles/aibi-marketing-campaign/install_package/AI-BI-Marketing-campaign.html
dbdemos-0.6.34.dist-info/LICENSE
dbdemos-0.6.34.dist-info/METADATA
dbdemos-0.6.34.dist-info/WHEEL
dbdemos-0.6.34.dist-info/top_level.txt
dbdemos-0.6.34.dist-info/RECORD
