Metadata-Version: 2.1
Name: dbdemos
Version: 0.6.34
Summary: Install databricks demos: notebooks, Delta Live Table Pipeline, DBSQL Dashboards, ML Models etc.
Home-page: https://github.com/databricks-demos/dbdemos
Author: Databricks
Author-email: ['quentin.ambard@databricks.com', 'cal.reynolds@databricks.com']
License: Databricks License
Requires-Python: >=3.7
License-File: LICENSE
Requires-Dist: requests
Requires-Dist: pandas
Requires-Dist: databricks-sdk >=0.38.0
